{
    "backend_name": "ibmq_belem",
    "backend_version": "1.0.47",
    "last_update_date": "2022-08-12T07:34:32+02:00",
    "qubits": [
        [
            {
                "date": "2022-08-12T07:10:22+02:00",
                "name": "T1",
                "unit": "us",
                "value": 85.2855263286923
            },
            {
                "date": "2022-08-12T06:41:27+02:00",
                "name": "T2",
                "unit": "us",
                "value": 125.38002467853137
            },
            {
                "date": "2022-08-12T07:34:32+02:00",
                "name": "frequency",
                "unit": "GHz",
                "value": 5.090208757914227
            },
            {
                "date": "2022-08-12T07:34:32+02:00",
                "name": "anharmonicity",
                "unit": "GHz",
                "value": -0.33612300518216515
            },
            {
                "date": "2022-08-12T06:33:57+02:00",
                "name": "readout_error",
                "unit": "",
                "value": 0.012799999999999923
            },
            {
                "date": "2022-08-12T06:33:57+02:00",
                "name": "prob_meas0_prep1",
                "unit": "",
                "value": 0.0212
            },
            {
                "date": "2022-08-12T06:33:57+02:00",
                "name": "prob_meas1_prep0",
                "unit": "",
                "value": 0.0043999999999999595
            },
            {
                "date": "2022-08-12T06:33:57+02:00",
                "name": "readout_length",
                "unit": "ns",
                "value": 5920
            }
        ],
        [
            {
                "date": "2022-08-12T07:17:26+02:00",
                "name": "T1",
                "unit": "us",
                "value": 77.74078179137426
            },
            {
                "date": "2022-08-12T06:42:59+02:00",
                "name": "T2",
                "unit": "us",
                "value": 82.42751199888654
            },
            {
                "date": "2022-08-12T07:34:32+02:00",
                "name": "frequency",
                "unit": "GHz",
                "value": 5.245502488671366
            },
            {
                "date": "2022-08-12T07:34:32+02:00",
                "name": "anharmonicity",
                "unit": "GHz",
                "value": -0.316572131412737
            },
            {
                "date": "2022-08-12T06:33:57+02:00",
                "name": "readout_error",
                "unit": "",
                "value": 0.028200000000000003
            },
            {
                "date": "2022-08-12T06:33:57+02:00",
                "name": "prob_meas0_prep1",
                "unit": "",
                "value": 0.04700000000000004
            },
            {
                "date": "2022-08-12T06:33:57+02:00",
                "name": "prob_meas1_prep0",
                "unit": "",
                "value": 0.0094
            },
            {
                "date": "2022-08-12T06:33:57+02:00",
                "name": "readout_length",
                "unit": "ns",
                "value": 5920
            }
        ],
        [
            {
                "date": "2022-08-11T22:30:35+02:00",
                "name": "T1",
                "unit": "us",
                "value": 89.36997538231522
            },
            {
                "date": "2022-08-12T06:41:27+02:00",
                "name": "T2",
                "unit": "us",
                "value": 44.58244922839811
            },
            {
                "date": "2022-08-12T07:34:32+02:00",
                "name": "frequency",
                "unit": "GHz",
                "value": 5.361497150899913
            },
            {
                "date": "2022-08-12T07:34:32+02:00",
                "name": "anharmonicity",
                "unit": "GHz",
                "value": -0.3306274884584928
            },
            {
                "date": "2022-08-12T06:33:57+02:00",
                "name": "readout_error",
                "unit": "",
                "value": 0.026899999999999924
            },
            {
                "date": "2022-08-12T06:33:57+02:00",
                "name": "prob_meas0_prep1",
                "unit": "",
                "value": 0.0466
            },
            {
                "date": "2022-08-12T06:33:57+02:00",
                "name": "prob_meas1_prep0",
                "unit": "",
                "value": 0.007199999999999984
            },
            {
                "date": "2022-08-12T06:33:57+02:00",
                "name": "readout_length",
                "unit": "ns",
                "value": 5920
            }
        ],
        [
            {
                "date": "2022-08-12T07:10:22+02:00",
                "name": "T1",
                "unit": "us",
                "value": 141.76819718441232
            },
            {
                "date": "2022-08-12T06:41:27+02:00",
                "name": "T2",
                "unit": "us",
                "value": 169.48259360513956
            },
            {
                "date": "2022-08-12T07:34:32+02:00",
                "name": "frequency",
                "unit": "GHz",
                "value": 5.17039668409254
            },
            {
                "date": "2022-08-12T07:34:32+02:00",
                "name": "anharmonicity",
                "unit": "GHz",
                "value": -0.33373922611368106
            },
            {
                "date": "2022-08-12T06:33:57+02:00",
                "name": "readout_error",
                "unit": "",
                "value": 0.0403
            },
            {
                "date": "2022-08-12T06:33:57+02:00",
                "name": "prob_meas0_prep1",
                "unit": "",
                "value": 0.06440000000000001
            },
            {
                "date": "2022-08-12T06:33:57+02:00",
                "name": "prob_meas1_prep0",
                "unit": "",
                "value": 0.0162
            },
            {
                "date": "2022-08-12T06:33:57+02:00",
                "name": "readout_length",
                "unit": "ns",
                "value": 5920
            }
        ],
        [
            {
                "date": "2022-08-12T07:17:26+02:00",
                "name": "T1",
                "unit": "us",
                "value": 87.76624990768416
            },
            {
                "date": "2022-08-12T06:42:59+02:00",
                "name": "T2",
                "unit": "us",
                "value": 143.35664212320992
            },
            {
                "date": "2022-08-12T07:34:32+02:00",
                "name": "frequency",
                "unit": "GHz",
                "value": 5.258664865821325
            },
            {
                "date": "2022-08-12T07:34:32+02:00",
                "name": "anharmonicity",
                "unit": "GHz",
                "value": -0.3313451432371279
            },
            {
                "date": "2022-08-12T06:33:57+02:00",
                "name": "readout_error",
                "unit": "",
                "value": 0.020199999999999996
            },
            {
                "date": "2022-08-12T06:33:57+02:00",
                "name": "prob_meas0_prep1",
                "unit": "",
                "value": 0.032200000000000006
            },
            {
                "date": "2022-08-12T06:33:57+02:00",
                "name": "prob_meas1_prep0",
                "unit": "",
                "value": 0.0082
            },
            {
                "date": "2022-08-12T06:33:57+02:00",
                "name": "readout_length",
                "unit": "ns",
                "value": 5920
            }
        ]
    ],
    "gates": [
        {
            "qubits": [
                0
            ],
            "gate": "id",
            "parameters": [
                {
                    "date": "2022-08-12T06:45:16+02:00",
                    "name": "gate_error",
                    "unit": "",
                    "value": 0.00020284675895189166
                },
                {
                    "date": "2022-08-12T07:34:32+02:00",
                    "name": "gate_length",
                    "unit": "ns",
                    "value": 35.55555555555556
                }
            ],
            "name": "id0"
        },
        {
            "qubits": [
                1
            ],
            "gate": "id",
            "parameters": [
                {
                    "date": "2022-08-12T06:48:35+02:00",
                    "name": "gate_error",
                    "unit": "",
                    "value": 0.001629867169665336
                },
                {
                    "date": "2022-08-12T07:34:32+02:00",
                    "name": "gate_length",
                    "unit": "ns",
                    "value": 35.55555555555556
                }
            ],
            "name": "id1"
        },
        {
            "qubits": [
                2
            ],
            "gate": "id",
            "parameters": [
                {
                    "date": "2022-08-12T06:45:16+02:00",
                    "name": "gate_error",
                    "unit": "",
                    "value": 0.0002717283330315684
                },
                {
                    "date": "2022-08-12T07:34:32+02:00",
                    "name": "gate_length",
                    "unit": "ns",
                    "value": 35.55555555555556
                }
            ],
            "name": "id2"
        },
        {
            "qubits": [
                3
            ],
            "gate": "id",
            "parameters": [
                {
                    "date": "2022-08-12T06:45:16+02:00",
                    "name": "gate_error",
                    "unit": "",
                    "value": 0.00034151142343338874
                },
                {
                    "date": "2022-08-12T07:34:32+02:00",
                    "name": "gate_length",
                    "unit": "ns",
                    "value": 35.55555555555556
                }
            ],
            "name": "id3"
        },
        {
            "qubits": [
                4
            ],
            "gate": "id",
            "parameters": [
                {
                    "date": "2022-08-12T06:48:35+02:00",
                    "name": "gate_error",
                    "unit": "",
                    "value": 0.0005128914273171778
                },
                {
                    "date": "2022-08-12T07:34:32+02:00",
                    "name": "gate_length",
                    "unit": "ns",
                    "value": 35.55555555555556
                }
            ],
            "name": "id4"
        },
        {
            "qubits": [
                0
            ],
            "gate": "rz",
            "parameters": [
                {
                    "date": "2022-08-12T07:34:32+02:00",
                    "name": "gate_error",
                    "unit": "",
                    "value": 0
                },
                {
                    "date": "2022-08-12T07:34:32+02:00",
                    "name": "gate_length",
                    "unit": "ns",
                    "value": 0
                }
            ],
            "name": "rz0"
        },
        {
            "qubits": [
                1
            ],
            "gate": "rz",
            "parameters": [
                {
                    "date": "2022-08-12T07:34:32+02:00",
                    "name": "gate_error",
                    "unit": "",
                    "value": 0
                },
                {
                    "date": "2022-08-12T07:34:32+02:00",
                    "name": "gate_length",
                    "unit": "ns",
                    "value": 0
                }
            ],
            "name": "rz1"
        },
        {
            "qubits": [
                2
            ],
            "gate": "rz",
            "parameters": [
                {
                    "date": "2022-08-12T07:34:32+02:00",
                    "name": "gate_error",
                    "unit": "",
                    "value": 0
                },
                {
                    "date": "2022-08-12T07:34:32+02:00",
                    "name": "gate_length",
                    "unit": "ns",
                    "value": 0
                }
            ],
            "name": "rz2"
        },
        {
            "qubits": [
                3
            ],
            "gate": "rz",
            "parameters": [
                {
                    "date": "2022-08-12T07:34:32+02:00",
                    "name": "gate_error",
                    "unit": "",
                    "value": 0
                },
                {
                    "date": "2022-08-12T07:34:32+02:00",
                    "name": "gate_length",
                    "unit": "ns",
                    "value": 0
                }
            ],
            "name": "rz3"
        },
        {
            "qubits": [
                4
            ],
            "gate": "rz",
            "parameters": [
                {
                    "date": "2022-08-12T07:34:32+02:00",
                    "name": "gate_error",
                    "unit": "",
                    "value": 0
                },
                {
                    "date": "2022-08-12T07:34:32+02:00",
                    "name": "gate_length",
                    "unit": "ns",
                    "value": 0
                }
            ],
            "name": "rz4"
        },
        {
            "qubits": [
                0
            ],
            "gate": "sx",
            "parameters": [
                {
                    "date": "2022-08-12T06:45:16+02:00",
                    "name": "gate_error",
                    "unit": "",
                    "value": 0.00020284675895189166
                },
                {
                    "date": "2022-08-12T07:34:32+02:00",
                    "name": "gate_length",
                    "unit": "ns",
                    "value": 35.55555555555556
                }
            ],
            "name": "sx0"
        },
        {
            "qubits": [
                1
            ],
            "gate": "sx",
            "parameters": [
                {
                    "date": "2022-08-12T06:48:35+02:00",
                    "name": "gate_error",
                    "unit": "",
                    "value": 0.001629867169665336
                },
                {
                    "date": "2022-08-12T07:34:32+02:00",
                    "name": "gate_length",
                    "unit": "ns",
                    "value": 35.55555555555556
                }
            ],
            "name": "sx1"
        },
        {
            "qubits": [
                2
            ],
            "gate": "sx",
            "parameters": [
                {
                    "date": "2022-08-12T06:45:16+02:00",
                    "name": "gate_error",
                    "unit": "",
                    "value": 0.0002717283330315684
                },
                {
                    "date": "2022-08-12T07:34:32+02:00",
                    "name": "gate_length",
                    "unit": "ns",
                    "value": 35.55555555555556
                }
            ],
            "name": "sx2"
        },
        {
            "qubits": [
                3
            ],
            "gate": "sx",
            "parameters": [
                {
                    "date": "2022-08-12T06:45:16+02:00",
                    "name": "gate_error",
                    "unit": "",
                    "value": 0.00034151142343338874
                },
                {
                    "date": "2022-08-12T07:34:32+02:00",
                    "name": "gate_length",
                    "unit": "ns",
                    "value": 35.55555555555556
                }
            ],
            "name": "sx3"
        },
        {
            "qubits": [
                4
            ],
            "gate": "sx",
            "parameters": [
                {
                    "date": "2022-08-12T06:48:35+02:00",
                    "name": "gate_error",
                    "unit": "",
                    "value": 0.0005128914273171778
                },
                {
                    "date": "2022-08-12T07:34:32+02:00",
                    "name": "gate_length",
                    "unit": "ns",
                    "value": 35.55555555555556
                }
            ],
            "name": "sx4"
        },
        {
            "qubits": [
                0
            ],
            "gate": "x",
            "parameters": [
                {
                    "date": "2022-08-12T06:45:16+02:00",
                    "name": "gate_error",
                    "unit": "",
                    "value": 0.00020284675895189166
                },
                {
                    "date": "2022-08-12T07:34:32+02:00",
                    "name": "gate_length",
                    "unit": "ns",
                    "value": 35.55555555555556
                }
            ],
            "name": "x0"
        },
        {
            "qubits": [
                1
            ],
            "gate": "x",
            "parameters": [
                {
                    "date": "2022-08-12T06:48:35+02:00",
                    "name": "gate_error",
                    "unit": "",
                    "value": 0.001629867169665336
                },
                {
                    "date": "2022-08-12T07:34:32+02:00",
                    "name": "gate_length",
                    "unit": "ns",
                    "value": 35.55555555555556
                }
            ],
            "name": "x1"
        },
        {
            "qubits": [
                2
            ],
            "gate": "x",
            "parameters": [
                {
                    "date": "2022-08-12T06:45:16+02:00",
                    "name": "gate_error",
                    "unit": "",
                    "value": 0.0002717283330315684
                },
                {
                    "date": "2022-08-12T07:34:32+02:00",
                    "name": "gate_length",
                    "unit": "ns",
                    "value": 35.55555555555556
                }
            ],
            "name": "x2"
        },
        {
            "qubits": [
                3
            ],
            "gate": "x",
            "parameters": [
                {
                    "date": "2022-08-12T06:45:16+02:00",
                    "name": "gate_error",
                    "unit": "",
                    "value": 0.00034151142343338874
                },
                {
                    "date": "2022-08-12T07:34:32+02:00",
                    "name": "gate_length",
                    "unit": "ns",
                    "value": 35.55555555555556
                }
            ],
            "name": "x3"
        },
        {
            "qubits": [
                4
            ],
            "gate": "x",
            "parameters": [
                {
                    "date": "2022-08-12T06:48:35+02:00",
                    "name": "gate_error",
                    "unit": "",
                    "value": 0.0005128914273171778
                },
                {
                    "date": "2022-08-12T07:34:32+02:00",
                    "name": "gate_length",
                    "unit": "ns",
                    "value": 35.55555555555556
                }
            ],
            "name": "x4"
        },
        {
            "qubits": [
                4,
                3
            ],
            "gate": "cx",
            "parameters": [
                {
                    "date": "2022-08-12T07:26:13+02:00",
                    "name": "gate_error",
                    "unit": "",
                    "value": 0.012945083734156981
                },
                {
                    "date": "2022-08-09T07:34:32+02:00",
                    "name": "gate_length",
                    "unit": "ns",
                    "value": 625.7777777777777
                }
            ],
            "name": "cx4_3"
        },
        {
            "qubits": [
                3,
                4
            ],
            "gate": "cx",
            "parameters": [
                {
                    "date": "2022-08-12T07:26:13+02:00",
                    "name": "gate_error",
                    "unit": "",
                    "value": 0.012945083734156981
                },
                {
                    "date": "2022-08-09T07:34:32+02:00",
                    "name": "gate_length",
                    "unit": "ns",
                    "value": 661.3333333333333
                }
            ],
            "name": "cx3_4"
        },
        {
            "qubits": [
                3,
                1
            ],
            "gate": "cx",
            "parameters": [
                {
                    "date": "2022-08-12T07:15:34+02:00",
                    "name": "gate_error",
                    "unit": "",
                    "value": 0.015965705265010816
                },
                {
                    "date": "2022-08-09T07:34:32+02:00",
                    "name": "gate_length",
                    "unit": "ns",
                    "value": 405.3333333333333
                }
            ],
            "name": "cx3_1"
        },
        {
            "qubits": [
                1,
                3
            ],
            "gate": "cx",
            "parameters": [
                {
                    "date": "2022-08-12T07:15:34+02:00",
                    "name": "gate_error",
                    "unit": "",
                    "value": 0.015965705265010816
                },
                {
                    "date": "2022-08-09T07:34:32+02:00",
                    "name": "gate_length",
                    "unit": "ns",
                    "value": 440.88888888888886
                }
            ],
            "name": "cx1_3"
        },
        {
            "qubits": [
                2,
                1
            ],
            "gate": "cx",
            "parameters": [
                {
                    "date": "2022-08-12T07:05:59+02:00",
                    "name": "gate_error",
                    "unit": "",
                    "value": 0.01018599928650038
                },
                {
                    "date": "2022-08-09T07:34:32+02:00",
                    "name": "gate_length",
                    "unit": "ns",
                    "value": 412.4444444444444
                }
            ],
            "name": "cx2_1"
        },
        {
            "qubits": [
                1,
                2
            ],
            "gate": "cx",
            "parameters": [
                {
                    "date": "2022-08-12T07:05:59+02:00",
                    "name": "gate_error",
                    "unit": "",
                    "value": 0.01018599928650038
                },
                {
                    "date": "2022-08-09T07:34:32+02:00",
                    "name": "gate_length",
                    "unit": "ns",
                    "value": 448
                }
            ],
            "name": "cx1_2"
        },
        {
            "qubits": [
                1,
                0
            ],
            "gate": "cx",
            "parameters": [
                {
                    "date": "2022-08-12T06:56:53+02:00",
                    "name": "gate_error",
                    "unit": "",
                    "value": 0.01939706919116735
                },
                {
                    "date": "2022-08-09T07:34:32+02:00",
                    "name": "gate_length",
                    "unit": "ns",
                    "value": 775.1111111111111
                }
            ],
            "name": "cx1_0"
        },
        {
            "qubits": [
                0,
                1
            ],
            "gate": "cx",
            "parameters": [
                {
                    "date": "2022-08-12T06:56:53+02:00",
                    "name": "gate_error",
                    "unit": "",
                    "value": 0.01939706919116735
                },
                {
                    "date": "2022-08-09T07:34:32+02:00",
                    "name": "gate_length",
                    "unit": "ns",
                    "value": 810.6666666666666
                }
            ],
            "name": "cx0_1"
        },
        {
            "qubits": [
                0
            ],
            "gate": "reset",
            "parameters": [
                {
                    "date": "2022-08-12T07:34:32+02:00",
                    "name": "gate_length",
                    "unit": "ns",
                    "value": 7911.11111111111
                }
            ],
            "name": "reset0"
        },
        {
            "qubits": [
                1
            ],
            "gate": "reset",
            "parameters": [
                {
                    "date": "2022-08-12T07:34:32+02:00",
                    "name": "gate_length",
                    "unit": "ns",
                    "value": 7911.11111111111
                }
            ],
            "name": "reset1"
        },
        {
            "qubits": [
                2
            ],
            "gate": "reset",
            "parameters": [
                {
                    "date": "2022-08-12T07:34:32+02:00",
                    "name": "gate_length",
                    "unit": "ns",
                    "value": 5955.555555555556
                }
            ],
            "name": "reset2"
        },
        {
            "qubits": [
                3
            ],
            "gate": "reset",
            "parameters": [
                {
                    "date": "2022-08-12T07:34:32+02:00",
                    "name": "gate_length",
                    "unit": "ns",
                    "value": 7911.11111111111
                }
            ],
            "name": "reset3"
        },
        {
            "qubits": [
                4
            ],
            "gate": "reset",
            "parameters": [
                {
                    "date": "2022-08-12T07:34:32+02:00",
                    "name": "gate_length",
                    "unit": "ns",
                    "value": 7911.11111111111
                }
            ],
            "name": "reset4"
        }
    ],
    "general": [
        {
            "date": "2022-08-12T07:34:32+02:00",
            "name": "jq_01",
            "unit": "GHz",
            "value": 0.0018736137364449847
        },
        {
            "date": "2022-08-12T07:34:32+02:00",
            "name": "zz_01",
            "unit": "GHz",
            "value": -5.778719017046504e-05
        },
        {
            "date": "2022-08-12T07:34:32+02:00",
            "name": "jq_12",
            "unit": "GHz",
            "value": 0.0020062596172337292
        },
        {
            "date": "2022-08-12T07:34:32+02:00",
            "name": "zz_12",
            "unit": "GHz",
            "value": -5.607853601551941e-05
        },
        {
            "date": "2022-08-12T07:34:32+02:00",
            "name": "jq_13",
            "unit": "GHz",
            "value": 0.0020039976609872224
        },
        {
            "date": "2022-08-12T07:34:32+02:00",
            "name": "zz_13",
            "unit": "GHz",
            "value": -5.2854062688980254e-05
        },
        {
            "date": "2022-08-12T07:34:32+02:00",
            "name": "jq_34",
            "unit": "GHz",
            "value": 0.0016737719182152912
        },
        {
            "date": "2022-08-12T07:34:32+02:00",
            "name": "zz_34",
            "unit": "GHz",
            "value": -3.628419642815204e-05
        }
    ]
}