{
    "backend_name": "ibmq_lima",
    "backend_version": "1.0.40",
    "last_update_date": "2022-11-10T07:37:45+01:00",
    "qubits": [
        [
            {
                "date": "2022-11-10T06:26:41+01:00",
                "name": "T1",
                "unit": "us",
                "value": 119.24159947228495
            },
            {
                "date": "2022-11-10T06:29:03+01:00",
                "name": "T2",
                "unit": "us",
                "value": 184.56959678402995
            },
            {
                "date": "2022-11-10T07:37:45+01:00",
                "name": "frequency",
                "unit": "GHz",
                "value": 5.029746240013726
            },
            {
                "date": "2022-11-10T07:37:45+01:00",
                "name": "anharmonicity",
                "unit": "GHz",
                "value": -0.33574155258829724
            },
            {
                "date": "2022-11-10T06:24:46+01:00",
                "name": "readout_error",
                "unit": "",
                "value": 0.015000000000000013
            },
            {
                "date": "2022-11-10T06:24:46+01:00",
                "name": "prob_meas0_prep1",
                "unit": "",
                "value": 0.0242
            },
            {
                "date": "2022-11-10T06:24:46+01:00",
                "name": "prob_meas1_prep0",
                "unit": "",
                "value": 0.0058
            },
            {
                "date": "2022-11-10T06:24:46+01:00",
                "name": "readout_length",
                "unit": "ns",
                "value": 5351.11111111111
            }
        ],
        [
            {
                "date": "2022-11-10T06:26:41+01:00",
                "name": "T1",
                "unit": "us",
                "value": 92.0517372860173
            },
            {
                "date": "2022-11-10T06:31:37+01:00",
                "name": "T2",
                "unit": "us",
                "value": 103.78702950519819
            },
            {
                "date": "2022-11-10T07:37:45+01:00",
                "name": "frequency",
                "unit": "GHz",
                "value": 5.127739233415157
            },
            {
                "date": "2022-11-10T07:37:45+01:00",
                "name": "anharmonicity",
                "unit": "GHz",
                "value": -0.3183491230373718
            },
            {
                "date": "2022-11-10T06:24:46+01:00",
                "name": "readout_error",
                "unit": "",
                "value": 0.022299999999999986
            },
            {
                "date": "2022-11-10T06:24:46+01:00",
                "name": "prob_meas0_prep1",
                "unit": "",
                "value": 0.03259999999999996
            },
            {
                "date": "2022-11-10T06:24:46+01:00",
                "name": "prob_meas1_prep0",
                "unit": "",
                "value": 0.012
            },
            {
                "date": "2022-11-10T06:24:46+01:00",
                "name": "readout_length",
                "unit": "ns",
                "value": 5351.11111111111
            }
        ],
        [
            {
                "date": "2022-11-10T06:26:41+01:00",
                "name": "T1",
                "unit": "us",
                "value": 95.51471878480707
            },
            {
                "date": "2022-11-10T06:29:03+01:00",
                "name": "T2",
                "unit": "us",
                "value": 132.80658193859873
            },
            {
                "date": "2022-11-10T07:37:45+01:00",
                "name": "frequency",
                "unit": "GHz",
                "value": 5.247351121800803
            },
            {
                "date": "2022-11-10T07:37:45+01:00",
                "name": "anharmonicity",
                "unit": "GHz",
                "value": -0.3336036607926792
            },
            {
                "date": "2022-11-10T06:24:46+01:00",
                "name": "readout_error",
                "unit": "",
                "value": 0.027099999999999902
            },
            {
                "date": "2022-11-10T06:24:46+01:00",
                "name": "prob_meas0_prep1",
                "unit": "",
                "value": 0.04079999999999995
            },
            {
                "date": "2022-11-10T06:24:46+01:00",
                "name": "prob_meas1_prep0",
                "unit": "",
                "value": 0.0134
            },
            {
                "date": "2022-11-10T06:24:46+01:00",
                "name": "readout_length",
                "unit": "ns",
                "value": 5351.11111111111
            }
        ],
        [
            {
                "date": "2022-11-10T06:26:41+01:00",
                "name": "T1",
                "unit": "us",
                "value": 86.96825941659347
            },
            {
                "date": "2022-11-10T06:29:03+01:00",
                "name": "T2",
                "unit": "us",
                "value": 30.303239992586036
            },
            {
                "date": "2022-11-10T07:37:45+01:00",
                "name": "frequency",
                "unit": "GHz",
                "value": 5.302520433395477
            },
            {
                "date": "2022-11-10T07:37:45+01:00",
                "name": "anharmonicity",
                "unit": "GHz",
                "value": -0.33124193185343576
            },
            {
                "date": "2022-11-10T06:24:46+01:00",
                "name": "readout_error",
                "unit": "",
                "value": 0.04679999999999995
            },
            {
                "date": "2022-11-10T06:24:46+01:00",
                "name": "prob_meas0_prep1",
                "unit": "",
                "value": 0.05779999999999996
            },
            {
                "date": "2022-11-10T06:24:46+01:00",
                "name": "prob_meas1_prep0",
                "unit": "",
                "value": 0.0358
            },
            {
                "date": "2022-11-10T06:24:46+01:00",
                "name": "readout_length",
                "unit": "ns",
                "value": 5351.11111111111
            }
        ],
        [
            {
                "date": "2022-11-10T06:26:41+01:00",
                "name": "T1",
                "unit": "us",
                "value": 21.998477229206614
            },
            {
                "date": "2022-11-10T06:31:37+01:00",
                "name": "T2",
                "unit": "us",
                "value": 18.277287376312437
            },
            {
                "date": "2022-11-10T07:37:45+01:00",
                "name": "frequency",
                "unit": "GHz",
                "value": 5.091996454821234
            },
            {
                "date": "2022-11-10T07:37:45+01:00",
                "name": "anharmonicity",
                "unit": "GHz",
                "value": -0.3344696566823515
            },
            {
                "date": "2022-11-10T06:24:46+01:00",
                "name": "readout_error",
                "unit": "",
                "value": 0.06169999999999998
            },
            {
                "date": "2022-11-10T06:24:46+01:00",
                "name": "prob_meas0_prep1",
                "unit": "",
                "value": 0.09919999999999995
            },
            {
                "date": "2022-11-10T06:24:46+01:00",
                "name": "prob_meas1_prep0",
                "unit": "",
                "value": 0.0242
            },
            {
                "date": "2022-11-10T06:24:46+01:00",
                "name": "readout_length",
                "unit": "ns",
                "value": 5351.11111111111
            }
        ]
    ],
    "gates": [
        {
            "qubits": [
                0
            ],
            "gate": "id",
            "parameters": [
                {
                    "date": "2022-11-10T06:36:48+01:00",
                    "name": "gate_error",
                    "unit": "",
                    "value": 0.00041628229173891105
                },
                {
                    "date": "2022-11-10T07:37:45+01:00",
                    "name": "gate_length",
                    "unit": "ns",
                    "value": 35.55555555555556
                }
            ],
            "name": "id0"
        },
        {
            "qubits": [
                1
            ],
            "gate": "id",
            "parameters": [
                {
                    "date": "2022-11-10T06:42:19+01:00",
                    "name": "gate_error",
                    "unit": "",
                    "value": 0.0008009361080051858
                },
                {
                    "date": "2022-11-10T07:37:45+01:00",
                    "name": "gate_length",
                    "unit": "ns",
                    "value": 35.55555555555556
                }
            ],
            "name": "id1"
        },
        {
            "qubits": [
                2
            ],
            "gate": "id",
            "parameters": [
                {
                    "date": "2022-11-10T06:36:48+01:00",
                    "name": "gate_error",
                    "unit": "",
                    "value": 0.0006024862921817284
                },
                {
                    "date": "2022-11-10T07:37:45+01:00",
                    "name": "gate_length",
                    "unit": "ns",
                    "value": 35.55555555555556
                }
            ],
            "name": "id2"
        },
        {
            "qubits": [
                3
            ],
            "gate": "id",
            "parameters": [
                {
                    "date": "2022-11-10T06:36:48+01:00",
                    "name": "gate_error",
                    "unit": "",
                    "value": 0.00040568672696072327
                },
                {
                    "date": "2022-11-10T07:37:45+01:00",
                    "name": "gate_length",
                    "unit": "ns",
                    "value": 35.55555555555556
                }
            ],
            "name": "id3"
        },
        {
            "qubits": [
                4
            ],
            "gate": "id",
            "parameters": [
                {
                    "date": "2022-11-10T06:42:19+01:00",
                    "name": "gate_error",
                    "unit": "",
                    "value": 0.0006837740901829095
                },
                {
                    "date": "2022-11-10T07:37:45+01:00",
                    "name": "gate_length",
                    "unit": "ns",
                    "value": 35.55555555555556
                }
            ],
            "name": "id4"
        },
        {
            "qubits": [
                0
            ],
            "gate": "rz",
            "parameters": [
                {
                    "date": "2022-11-10T07:37:45+01:00",
                    "name": "gate_error",
                    "unit": "",
                    "value": 0
                },
                {
                    "date": "2022-11-10T07:37:45+01:00",
                    "name": "gate_length",
                    "unit": "ns",
                    "value": 0
                }
            ],
            "name": "rz0"
        },
        {
            "qubits": [
                1
            ],
            "gate": "rz",
            "parameters": [
                {
                    "date": "2022-11-10T07:37:45+01:00",
                    "name": "gate_error",
                    "unit": "",
                    "value": 0
                },
                {
                    "date": "2022-11-10T07:37:45+01:00",
                    "name": "gate_length",
                    "unit": "ns",
                    "value": 0
                }
            ],
            "name": "rz1"
        },
        {
            "qubits": [
                2
            ],
            "gate": "rz",
            "parameters": [
                {
                    "date": "2022-11-10T07:37:45+01:00",
                    "name": "gate_error",
                    "unit": "",
                    "value": 0
                },
                {
                    "date": "2022-11-10T07:37:45+01:00",
                    "name": "gate_length",
                    "unit": "ns",
                    "value": 0
                }
            ],
            "name": "rz2"
        },
        {
            "qubits": [
                3
            ],
            "gate": "rz",
            "parameters": [
                {
                    "date": "2022-11-10T07:37:45+01:00",
                    "name": "gate_error",
                    "unit": "",
                    "value": 0
                },
                {
                    "date": "2022-11-10T07:37:45+01:00",
                    "name": "gate_length",
                    "unit": "ns",
                    "value": 0
                }
            ],
            "name": "rz3"
        },
        {
            "qubits": [
                4
            ],
            "gate": "rz",
            "parameters": [
                {
                    "date": "2022-11-10T07:37:45+01:00",
                    "name": "gate_error",
                    "unit": "",
                    "value": 0
                },
                {
                    "date": "2022-11-10T07:37:45+01:00",
                    "name": "gate_length",
                    "unit": "ns",
                    "value": 0
                }
            ],
            "name": "rz4"
        },
        {
            "qubits": [
                0
            ],
            "gate": "sx",
            "parameters": [
                {
                    "date": "2022-11-10T06:36:48+01:00",
                    "name": "gate_error",
                    "unit": "",
                    "value": 0.00041628229173891105
                },
                {
                    "date": "2022-11-10T07:37:45+01:00",
                    "name": "gate_length",
                    "unit": "ns",
                    "value": 35.55555555555556
                }
            ],
            "name": "sx0"
        },
        {
            "qubits": [
                1
            ],
            "gate": "sx",
            "parameters": [
                {
                    "date": "2022-11-10T06:42:19+01:00",
                    "name": "gate_error",
                    "unit": "",
                    "value": 0.0008009361080051858
                },
                {
                    "date": "2022-11-10T07:37:45+01:00",
                    "name": "gate_length",
                    "unit": "ns",
                    "value": 35.55555555555556
                }
            ],
            "name": "sx1"
        },
        {
            "qubits": [
                2
            ],
            "gate": "sx",
            "parameters": [
                {
                    "date": "2022-11-10T06:36:48+01:00",
                    "name": "gate_error",
                    "unit": "",
                    "value": 0.0006024862921817284
                },
                {
                    "date": "2022-11-10T07:37:45+01:00",
                    "name": "gate_length",
                    "unit": "ns",
                    "value": 35.55555555555556
                }
            ],
            "name": "sx2"
        },
        {
            "qubits": [
                3
            ],
            "gate": "sx",
            "parameters": [
                {
                    "date": "2022-11-10T06:36:48+01:00",
                    "name": "gate_error",
                    "unit": "",
                    "value": 0.00040568672696072327
                },
                {
                    "date": "2022-11-10T07:37:45+01:00",
                    "name": "gate_length",
                    "unit": "ns",
                    "value": 35.55555555555556
                }
            ],
            "name": "sx3"
        },
        {
            "qubits": [
                4
            ],
            "gate": "sx",
            "parameters": [
                {
                    "date": "2022-11-10T06:42:19+01:00",
                    "name": "gate_error",
                    "unit": "",
                    "value": 0.0006837740901829095
                },
                {
                    "date": "2022-11-10T07:37:45+01:00",
                    "name": "gate_length",
                    "unit": "ns",
                    "value": 35.55555555555556
                }
            ],
            "name": "sx4"
        },
        {
            "qubits": [
                0
            ],
            "gate": "x",
            "parameters": [
                {
                    "date": "2022-11-10T06:36:48+01:00",
                    "name": "gate_error",
                    "unit": "",
                    "value": 0.00041628229173891105
                },
                {
                    "date": "2022-11-10T07:37:45+01:00",
                    "name": "gate_length",
                    "unit": "ns",
                    "value": 35.55555555555556
                }
            ],
            "name": "x0"
        },
        {
            "qubits": [
                1
            ],
            "gate": "x",
            "parameters": [
                {
                    "date": "2022-11-10T06:42:19+01:00",
                    "name": "gate_error",
                    "unit": "",
                    "value": 0.0008009361080051858
                },
                {
                    "date": "2022-11-10T07:37:45+01:00",
                    "name": "gate_length",
                    "unit": "ns",
                    "value": 35.55555555555556
                }
            ],
            "name": "x1"
        },
        {
            "qubits": [
                2
            ],
            "gate": "x",
            "parameters": [
                {
                    "date": "2022-11-10T06:36:48+01:00",
                    "name": "gate_error",
                    "unit": "",
                    "value": 0.0006024862921817284
                },
                {
                    "date": "2022-11-10T07:37:45+01:00",
                    "name": "gate_length",
                    "unit": "ns",
                    "value": 35.55555555555556
                }
            ],
            "name": "x2"
        },
        {
            "qubits": [
                3
            ],
            "gate": "x",
            "parameters": [
                {
                    "date": "2022-11-10T06:36:48+01:00",
                    "name": "gate_error",
                    "unit": "",
                    "value": 0.00040568672696072327
                },
                {
                    "date": "2022-11-10T07:37:45+01:00",
                    "name": "gate_length",
                    "unit": "ns",
                    "value": 35.55555555555556
                }
            ],
            "name": "x3"
        },
        {
            "qubits": [
                4
            ],
            "gate": "x",
            "parameters": [
                {
                    "date": "2022-11-10T06:42:19+01:00",
                    "name": "gate_error",
                    "unit": "",
                    "value": 0.0006837740901829095
                },
                {
                    "date": "2022-11-10T07:37:45+01:00",
                    "name": "gate_length",
                    "unit": "ns",
                    "value": 35.55555555555556
                }
            ],
            "name": "x4"
        },
        {
            "qubits": [
                4,
                3
            ],
            "gate": "cx",
            "parameters": [
                {
                    "date": "2022-11-10T07:37:45+01:00",
                    "name": "gate_error",
                    "unit": "",
                    "value": 0.02055414728543717
                },
                {
                    "date": "2022-11-07T07:37:45+01:00",
                    "name": "gate_length",
                    "unit": "ns",
                    "value": 483.55555555555554
                }
            ],
            "name": "cx4_3"
        },
        {
            "qubits": [
                3,
                4
            ],
            "gate": "cx",
            "parameters": [
                {
                    "date": "2022-11-10T07:37:45+01:00",
                    "name": "gate_error",
                    "unit": "",
                    "value": 0.02055414728543717
                },
                {
                    "date": "2022-11-07T07:37:45+01:00",
                    "name": "gate_length",
                    "unit": "ns",
                    "value": 519.1111111111111
                }
            ],
            "name": "cx3_4"
        },
        {
            "qubits": [
                0,
                1
            ],
            "gate": "cx",
            "parameters": [
                {
                    "date": "2022-11-10T07:26:50+01:00",
                    "name": "gate_error",
                    "unit": "",
                    "value": 0.0078035352322305684
                },
                {
                    "date": "2022-11-07T07:37:45+01:00",
                    "name": "gate_length",
                    "unit": "ns",
                    "value": 305.77777777777777
                }
            ],
            "name": "cx0_1"
        },
        {
            "qubits": [
                1,
                0
            ],
            "gate": "cx",
            "parameters": [
                {
                    "date": "2022-11-10T07:26:50+01:00",
                    "name": "gate_error",
                    "unit": "",
                    "value": 0.0078035352322305684
                },
                {
                    "date": "2022-11-07T07:37:45+01:00",
                    "name": "gate_length",
                    "unit": "ns",
                    "value": 341.3333333333333
                }
            ],
            "name": "cx1_0"
        },
        {
            "qubits": [
                3,
                1
            ],
            "gate": "cx",
            "parameters": [
                {
                    "date": "2022-11-10T07:10:38+01:00",
                    "name": "gate_error",
                    "unit": "",
                    "value": 0.014796116944965243
                },
                {
                    "date": "2022-11-07T07:37:45+01:00",
                    "name": "gate_length",
                    "unit": "ns",
                    "value": 462.2222222222222
                }
            ],
            "name": "cx3_1"
        },
        {
            "qubits": [
                1,
                3
            ],
            "gate": "cx",
            "parameters": [
                {
                    "date": "2022-11-10T07:10:38+01:00",
                    "name": "gate_error",
                    "unit": "",
                    "value": 0.014796116944965243
                },
                {
                    "date": "2022-11-07T07:37:45+01:00",
                    "name": "gate_length",
                    "unit": "ns",
                    "value": 497.77777777777777
                }
            ],
            "name": "cx1_3"
        },
        {
            "qubits": [
                2,
                1
            ],
            "gate": "cx",
            "parameters": [
                {
                    "date": "2022-11-10T06:56:10+01:00",
                    "name": "gate_error",
                    "unit": "",
                    "value": 0.0076381030607377
                },
                {
                    "date": "2022-11-07T07:37:45+01:00",
                    "name": "gate_length",
                    "unit": "ns",
                    "value": 298.66666666666663
                }
            ],
            "name": "cx2_1"
        },
        {
            "qubits": [
                1,
                2
            ],
            "gate": "cx",
            "parameters": [
                {
                    "date": "2022-11-10T06:56:10+01:00",
                    "name": "gate_error",
                    "unit": "",
                    "value": 0.0076381030607377
                },
                {
                    "date": "2022-11-07T07:37:45+01:00",
                    "name": "gate_length",
                    "unit": "ns",
                    "value": 334.22222222222223
                }
            ],
            "name": "cx1_2"
        },
        {
            "qubits": [
                0
            ],
            "gate": "reset",
            "parameters": [
                {
                    "date": "2022-11-10T07:37:45+01:00",
                    "name": "gate_length",
                    "unit": "ns",
                    "value": 5742.222222222222
                }
            ],
            "name": "reset0"
        },
        {
            "qubits": [
                1
            ],
            "gate": "reset",
            "parameters": [
                {
                    "date": "2022-11-10T07:37:45+01:00",
                    "name": "gate_length",
                    "unit": "ns",
                    "value": 5742.222222222222
                }
            ],
            "name": "reset1"
        },
        {
            "qubits": [
                2
            ],
            "gate": "reset",
            "parameters": [
                {
                    "date": "2022-11-10T07:37:45+01:00",
                    "name": "gate_length",
                    "unit": "ns",
                    "value": 5742.222222222222
                }
            ],
            "name": "reset2"
        },
        {
            "qubits": [
                3
            ],
            "gate": "reset",
            "parameters": [
                {
                    "date": "2022-11-10T07:37:45+01:00",
                    "name": "gate_length",
                    "unit": "ns",
                    "value": 5742.222222222222
                }
            ],
            "name": "reset3"
        },
        {
            "qubits": [
                4
            ],
            "gate": "reset",
            "parameters": [
                {
                    "date": "2022-11-10T07:37:45+01:00",
                    "name": "gate_length",
                    "unit": "ns",
                    "value": 5742.222222222222
                }
            ],
            "name": "reset4"
        }
    ],
    "general": [
        {
            "date": "2022-11-10T07:37:45+01:00",
            "name": "jq_01",
            "unit": "GHz",
            "value": 0.001764809587423861
        },
        {
            "date": "2022-11-10T07:37:45+01:00",
            "name": "zz_01",
            "unit": "GHz",
            "value": -4.269674439106963e-05
        },
        {
            "date": "2022-11-10T07:37:45+01:00",
            "name": "jq_12",
            "unit": "GHz",
            "value": 0.0018768425276207256
        },
        {
            "date": "2022-11-10T07:37:45+01:00",
            "name": "zz_12",
            "unit": "GHz",
            "value": -4.896566658931517e-05
        },
        {
            "date": "2022-11-10T07:37:45+01:00",
            "name": "jq_13",
            "unit": "GHz",
            "value": 0.0018961548008719934
        },
        {
            "date": "2022-11-10T07:37:45+01:00",
            "name": "zz_13",
            "unit": "GHz",
            "value": -6.0602970191985954e-05
        },
        {
            "date": "2022-11-10T07:37:45+01:00",
            "name": "jq_34",
            "unit": "GHz",
            "value": 0.001855162498517866
        },
        {
            "date": "2022-11-10T07:37:45+01:00",
            "name": "zz_34",
            "unit": "GHz",
            "value": -7.012711532075646e-05
        }
    ]
}